whatshow_phy_detect_ep/EP.py
whatshow_phy_detect_ep/__init__.py
whatshow_phy_detect_ep-1.0.5.dist-info/METADATA
whatshow_phy_detect_ep-1.0.5.dist-info/WHEEL
whatshow_phy_detect_ep-1.0.5.dist-info/top_level.txt
whatshow_phy_detect_ep-1.0.5.dist-info/RECORD
